content_aware_timelapse/__init__.py
content_aware_timelapse/cat_pipelines.py
content_aware_timelapse/catcli_ui.py
content_aware_timelapse/frames_to_vectors/__init__.py
content_aware_timelapse/frames_to_vectors/conversion.py
content_aware_timelapse/frames_to_vectors/conversion_types.py
content_aware_timelapse/frames_to_vectors/vector_computation/__init__.py
content_aware_timelapse/frames_to_vectors/vector_computation/compute_vectors_clip.py
content_aware_timelapse/frames_to_vectors/vector_computation/compute_vectors_vit.py
content_aware_timelapse/frames_to_vectors/vector_computation/gpu_model_management.py
content_aware_timelapse/frames_to_vectors/vector_points_of_interest.py
content_aware_timelapse/frames_to_vectors/vector_scoring.py
content_aware_timelapse/gpu_discovery.py
content_aware_timelapse/py.typed
content_aware_timelapse/timeout_common.py
content_aware_timelapse/vector_file.py
content_aware_timelapse/viderator/__init__.py
content_aware_timelapse/viderator/frames_in_video.py
content_aware_timelapse/viderator/html_on_image/__init__.py
content_aware_timelapse/viderator/html_on_image/assets/__init__.py
content_aware_timelapse/viderator/html_on_image/assets/simple_thumbnail_overlay_template.html.jinja2
content_aware_timelapse/viderator/html_on_image/overlay_on_image.py
content_aware_timelapse/viderator/html_on_image/read_html_template.py
content_aware_timelapse/viderator/image_common.py
content_aware_timelapse/viderator/iterator_common.py
content_aware_timelapse/viderator/iterator_on_disk.py
content_aware_timelapse/viderator/video_common.py
content_aware_timelapse/viderator/viderator_types.py
content_aware_timelapse-0.17.3.dist-info/METADATA
content_aware_timelapse-0.17.3.dist-info/WHEEL
content_aware_timelapse-0.17.3.dist-info/licenses/AUTHORS.md
content_aware_timelapse-0.17.3.dist-info/RECORD
