Metadata-Version: 2.4
Name: content_aware_timelapse
Version: 0.17.3
Summary: Create timelapses from video that change speed based on the content found in the video.
License-File: AUTHORS.md
Author: Devon Bray
Requires-Python: >=3.10,<4.0
Classifier: Programming Language :: Python :: 3
Classifier: Programming Language :: Python :: 3.10
Classifier: Programming Language :: Python :: 3.11
Classifier: Programming Language :: Python :: 3.12
Classifier: Programming Language :: Python :: 3.13
Classifier: Programming Language :: Python :: 3.14
Requires-Dist: bonus-click (==0.3.0)
Requires-Dist: click (>=8.1.7,<9.0.0)
Requires-Dist: click-option-group (>=0.5.9,<0.6.0)
Requires-Dist: ffmpeg-python (>=0.2.0,<0.3.0)
Requires-Dist: ftfy (>=6.3.1,<7.0.0)
Requires-Dist: h5py (>=3.12.1,<4.0.0)
Requires-Dist: hdf5plugin (>=5.1.0,<6.0.0)
Requires-Dist: html2image (>=2.0.7,<3.0.0)
Requires-Dist: joblib (>=1.4.2,<2.0.0)
Requires-Dist: matplotlib (>=3.10.3,<4.0.0)
Requires-Dist: more-itertools (>=10.5.0,<11.0.0)
Requires-Dist: nvsmi (>=0.4.2,<0.5.0)
Requires-Dist: openai-clip (>=1.0.1,<2.0.0)
Requires-Dist: opencv-python (>=4.10.0.84,<5.0.0.0)
Requires-Dist: pandas (>=2.2.3,<3.0.0)
Requires-Dist: pillow (>=10.4.0,<11.0.0)
Requires-Dist: pkginfo (>=1.12.1.2,<2.0.0.0)
Requires-Dist: pympler (>=1.1,<2.0)
Requires-Dist: regex (>=2024.11.6,<2025.0.0)
Requires-Dist: scikit-learn (>=1.6.1,<2.0.0)
Requires-Dist: sentinels (>=1.0.0,<2.0.0)
Requires-Dist: setuptools (<81)
Requires-Dist: tabulate (>=0.9.0,<0.10.0)
Requires-Dist: timm (>=1.0.15,<2.0.0)
Requires-Dist: torch (>=2.4.1,<3.0.0)
Requires-Dist: torchvision (>=0.19.1,<0.20.0)
Requires-Dist: tqdm (>=4.66.5,<5.0.0)
